buckia/__init__.py
buckia/cli.py
buckia/client.py
buckia/config.py
buckia/pdf.py
buckia/security/__init__.py
buckia/security/token_manager.py
buckia/sync/__init__.py
buckia/sync/b2.py
buckia/sync/base.py
buckia/sync/bunny.py
buckia/sync/factory.py
buckia/sync/bunnycdn/CDN.py
buckia/sync/bunnycdn/Storage.py
buckia/sync/bunnycdn/__init__.py
buckia-0.5.2.dist-info/METADATA
buckia-0.5.2.dist-info/WHEEL
buckia-0.5.2.dist-info/entry_points.txt
buckia-0.5.2.dist-info/top_level.txt
buckia-0.5.2.dist-info/RECORD
