Metadata-Version: 2.4
Name: buckia
Version: 0.5.2
Summary: Multi-platform, multi-backend storage bucket synchronization
Author-email: Henrik Vendelbo <hvendelbo+pypi@gmail.com>
License: AGPL-3.0
Project-URL: Homepage, https://github.com/thepian/buckia
Project-URL: Repository, https://github.com/thepian/buckia
Project-URL: Issues, https://github.com/thepian/buckia/issues
Keywords: storage,bucket,sync,bunny,s3,linode,b2,backblaze
Classifier: Development Status :: 3 - Alpha
Classifier: Intended Audience :: Developers
Classifier: License :: OSI Approved :: GNU Affero General Public License v3
Classifier: Programming Language :: Python :: 3
Classifier: Programming Language :: Python :: 3.10
Classifier: Programming Language :: Python :: 3.11
Classifier: Programming Language :: Python :: 3.12
Classifier: Topic :: System :: Archiving :: Backup
Classifier: Topic :: System :: Archiving :: Mirroring
Requires-Python: >=3.10
Requires-Dist: requests>=2.25.0
Requires-Dist: pyyaml>=5.4.0
Requires-Dist: keyring>=24.0.0
Requires-Dist: pytest>=8.3.5
Requires-Dist: python-dotenv>=1.1.0
Requires-Dist: weasyprint>=65.1
Provides-Extra: bunny
Requires-Dist: bunnycdnpython>=0.0.8; extra == "bunny"
Provides-Extra: s3
Requires-Dist: boto3>=1.17.0; extra == "s3"
Provides-Extra: linode
Requires-Dist: linode-api4>=5.0.0; extra == "linode"
Provides-Extra: b2
Requires-Dist: b2sdk<3,>=2.8.0; extra == "b2"
Provides-Extra: pdf
Requires-Dist: weasyprint>=62.0; extra == "pdf"
Provides-Extra: dev
Requires-Dist: pytest>=6.2.0; extra == "dev"
Requires-Dist: pytest-cov>=2.10.1; extra == "dev"
Requires-Dist: pytest-env>=0.8.1; extra == "dev"
Requires-Dist: pytest-timeout>=2.1.0; extra == "dev"
Requires-Dist: black>=23.12.1; extra == "dev"
Requires-Dist: flake8>=7.0.0; extra == "dev"
Requires-Dist: mypy>=1.15.0; extra == "dev"
Requires-Dist: pre-commit>=3.5.0; extra == "dev"
Requires-Dist: isort>=5.13.2; extra == "dev"
Requires-Dist: types-PyYAML; extra == "dev"
Requires-Dist: types-requests; extra == "dev"
